adafruit_circuitpython_wm8960-1.0.5.dist-info/licenses/LICENSE
adafruit_wm8960/__init__.py
adafruit_wm8960/advanced.py
adafruit_circuitpython_wm8960-1.0.5.dist-info/METADATA
adafruit_circuitpython_wm8960-1.0.5.dist-info/WHEEL
adafruit_circuitpython_wm8960-1.0.5.dist-info/top_level.txt
adafruit_circuitpython_wm8960-1.0.5.dist-info/RECORD
