Metadata-Version: 2.4
Name: adafruit-circuitpython-wm8960
Version: 1.0.5
Summary: CircuitPython driver for WM8960 Stereo CODEC
Author-email: Adafruit Industries <circuitpython@adafruit.com>, Cooper Dalrymple <me@dcdalrymple.com>
License: MIT
Project-URL: Homepage, https://github.com/adafruit/Adafruit_CircuitPython_WM8960
Keywords: adafruit,blinka,circuitpython,micropython,codec,dac,adc,wm8960
Classifier: Intended Audience :: Developers
Classifier: Topic :: Software Development :: Libraries
Classifier: Topic :: Software Development :: Embedded Systems
Classifier: Topic :: System :: Hardware
Classifier: License :: OSI Approved :: MIT License
Classifier: Programming Language :: Python :: 3
License-File: LICENSE
Requires-Dist: adafruit-circuitpython-busdevice
Requires-Dist: adafruit-circuitpython-simplemath
Provides-Extra: optional
Dynamic: license-file
